adblock_decoder/__init__.py
adblock_decoder/cli.py
adblock_decoder/exceptions.py
adblock_decoder/core/__init__.py
adblock_decoder/core/adblock2hosts.py
adblock_decoder/core/adblock2plain.py
adblock_decoder/core/base.py
adblock_decoder/core/io_base.py
adblock_decoder-1.2.1.dist-info/LICENSE
adblock_decoder-1.2.1.dist-info/METADATA
adblock_decoder-1.2.1.dist-info/WHEEL
adblock_decoder-1.2.1.dist-info/entry_points.txt
adblock_decoder-1.2.1.dist-info/top_level.txt
adblock_decoder-1.2.1.dist-info/RECORD
