Metadata-Version: 2.1
Name: adblock-decoder
Version: 1.2.1
Summary: A set of tool for the decoding and conversion of AdBlock and Filter Lists.
Home-page: https://github.com/PyFunceble/adblock-decoder
Author: funilrys
Author-email: contact@funilrys.com
License: Apache 2.0
Project-URL: Funding, https://github.com/sponsors/funilrys
Project-URL: Source, https://github.com/PyFunceble/adblock-decoder
Project-URL: Tracker, https://github.com/funilrys/PyFunceble/issues
Keywords: PyFunceble,AdBlock,Filter,list,decoder
Platform: any
Classifier: Environment :: Console
Classifier: Topic :: Internet
Classifier: Development Status :: 5 - Production/Stable
Classifier: Intended Audience :: Developers
Classifier: Intended Audience :: Information Technology
Classifier: Intended Audience :: System Administrators
Classifier: Intended Audience :: Other Audience
Classifier: Programming Language :: Python
Classifier: Programming Language :: Python :: 3
Classifier: License :: OSI Approved
Requires-Python: >=3.6, <4
Requires-Dist: PyFunceble-dev (>=4.0.0b1)
